Metadata-Version: 1.1
Name: dmaudit
Version: 0.9.0
Summary: dmaudit generates data management audit reports
Home-page: https://github.com/JIC-CSB/dmaudit
Author: Tjelvar Olsson
Author-email: tjelvar.olsson@jic.ac.uk
License: MIT
Download-URL: https://github.com/JIC-CSB/dmaudit/tarball/0.9.0
Platform: UNKNOWN
